glmfpackage/__init__.py
glmfpackage/test_hello.py
glmfpackage/version.py
GLMFPackage-0.0.7.dist-info/METADATA
GLMFPackage-0.0.7.dist-info/WHEEL
GLMFPackage-0.0.7.dist-info/entry_points.txt
GLMFPackage-0.0.7.dist-info/top_level.txt
GLMFPackage-0.0.7.dist-info/RECORD
