Metadata-Version: 2.1
Name: GLMFPackage
Version: 0.0.7
Summary: A GLMF library package
Home-page: https://boutique.ed-diamond.com/
Author: Fred
Author-email: fritz.smh@gmail.com
License: UNKNOWN
Platform: UNKNOWN
Classifier: Programming Language :: Python :: 3
Classifier: License :: OSI Approved :: MIT License
Classifier: Operating System :: OS Independent
Requires-Python: >=3.6
